Workbook
Name Aport: 'Investimentos Matiz'!$D$20
Name Patrimônio: 'Investimentos Matiz'!$D$23
Name Quantidade_Anos: 'Investimentos Matiz'!$D$21
Name Rendimento_Carteira: 'Investimentos Matiz'!$D$16
Name Salário: 'Investimentos Matiz'!$D$15
Name Sugestão_de_Investimento: 'Investimentos Matiz'!$D$17
Name Taxa_Mensal: 'Investimentos Matiz'!$D$22

Sheet Investimentos Matiz
B14: Configurações
B15: Salário | D15: 2000
B16: Rendimento Carteira | D16: 0.006
B17: Sugestão de Investimento | D17: =D15*30% -> 600
B19: Investimento Mensal
B20: Quanto investir por mês? | D20: 200
B21: Por quantos anos? | D21: 5
B22: Qual taxa de rendimento mensal? | D22: 0.0108
B23: Quanto de patrimônio acumulado? | D23: =FV(Taxa_Mensal,Quantidade_Anos*12,Aport*-1) -> 16760.804
B24: Quanto é os dividendos mensais? | D24: =Patrimônio*Rendimento_Carteira -> 100.56482
B26: Cenários | D26: Dividendo
A27: 2 | B27: Quanto em 2 anos? | C27: =FV(Taxa_Mensal,$A27*12,Aport*-1) -> 5446.1727 | D27: =C27*Rendimento_Carteira -> 32.677036
A28: 5 | B28: Quanto em 5 anos? | C28: =FV(Taxa_Mensal,$A28*12,Aport*-1) -> 16760.804 | D28: =C28*Rendimento_Carteira -> 100.56482
A29: 10 | B29: Quanto em 10 anos? | C29: =FV(Taxa_Mensal,$A29*12,Aport*-1) -> 48691.533 | D29: =C29*Rendimento_Carteira -> 292.1492
A30: 20 | B30: Quanto em 20 anos? | C30: =FV(Taxa_Mensal,$A30*12,Aport*-1) -> 225409.8 | D30: =C30*Rendimento_Carteira -> 1352.4588
A31: 30 | B31: Quantos em 30 anos? | C31: =FV(Taxa_Mensal,$A31*12,Aport*-1) -> 866780.96 | D31: =C31*Rendimento_Carteira -> 5200.6858
B35: PERFIL | C35: Agressivo
B36: Valor a ser Investido Por Mês | C36: =Aport -> 200
B38: Tipo de FII | C38: Pencentual Sugerido | D38: Valores
B39: PAPEL | C39: =VLOOKUP($C$35&"-"&$B39,'Tabela de Apoio'!A3:$D$20,4,FALSE) -> 0.5 | D39: =$C39*$C$36 -> 100
B40: TIJOLO | C40: =VLOOKUP($C$35&"-"&$B40,'Tabela de Apoio'!A4:$D$20,4,FALSE) -> 0.1 | D40: =$C40*$C$36 -> 20
B41: HÍBRIDOS | C41: =VLOOKUP($C$35&"-"&$B41,'Tabela de Apoio'!A5:$D$20,4,FALSE) -> 0.05 | D41: =$C41*$C$36 -> 10
B42: FOFs | C42: =VLOOKUP($C$35&"-"&$B42,'Tabela de Apoio'!A6:$D$20,4,FALSE) -> 0.05 | D42: =$C42*$C$36 -> 10
B43: DESENVOLVIMENTO | C43: =VLOOKUP($C$35&"-"&$B43,'Tabela de Apoio'!A7:$D$20,4,FALSE) -> 0.2 | D43: =$C43*$C$36 -> 40
B44: HOTELARIAS | C44: =VLOOKUP($C$35&"-"&$B44,'Tabela de Apoio'!A8:$D$20,4,FALSE) -> 0.1 | D44: =$C44*$C$36 -> 20
B45: TOTAL | D45: =SUM(D39:D44) -> 200

Sheet Tabela de Apoio
A2: CHAVE | B2: PERFIL | C2: TIPO DE FII | D2: %
A3: =$B3&"-"&C3 -> Conservador-PAPEL | B3: Conservador | C3: PAPEL | D3: 0.3 | H3: %
A4: =$B4&"-"&C4 -> Conservador-TIJOLO | B4: Conservador | C4: TIJOLO | D4: 0.5 | G4: Moderado-TIJOLO | H4: =VLOOKUP(G4,A3:D20,4,FALSE) -> 0.35
A5: =$B5&"-"&C5 -> Conservador-HÍBRIDOS | B5: Conservador | C5: HÍBRIDOS | D5: 0.1
A6: =$B6&"-"&C6 -> Conservador-FOFs | B6: Conservador | C6: FOFs | D6: 0.1
A7: =$B7&"-"&C7 -> Conservador-DESENVOLVIMENTO | B7: Conservador | C7: DESENVOLVIMENTO | D7: 0
A8: =$B8&"-"&C8 -> Conservador-HOTELARIAS | B8: Conservador | C8: HOTELARIAS | D8: 0
A9: =$B9&"-"&C9 -> Moderado-PAPEL | B9: Moderado | C9: PAPEL | D9: 0.32
A10: =$B10&"-"&C10 -> Moderado-TIJOLO | B10: Moderado | C10: TIJOLO | D10: 0.35
A11: =$B11&"-"&C11 -> Moderado-HÍBRIDOS | B11: Moderado | C11: HÍBRIDOS | D11: 0.08
A12: =$B12&"-"&C12 -> Moderado-FOFs | B12: Moderado | C12: FOFs | D12: 0.05
A13: =$B13&"-"&C13 -> Moderado-DESENVOLVIMENTO | B13: Moderado | C13: DESENVOLVIMENTO | D13: 0.1
A14: =$B14&"-"&C14 -> Moderado-HOTELARIAS | B14: Moderado | C14: HOTELARIAS | D14: 0.1
A15: =$B15&"-"&C15 -> Agressivo-PAPEL | B15: Agressivo | C15: PAPEL | D15: 0.5
A16: =$B16&"-"&C16 -> Agressivo-TIJOLO | B16: Agressivo | C16: TIJOLO | D16: 0.1
... A20: =$B20&"-"&C20 -> Agressivo-HOTELARIAS | B20: Agressivo | C20: HOTELARIAS | D20: 0.1

Sheet Q&A
B2: Esta planilha representa um Simulador Financeiro
B9: Fórmulas
B10: Fórmula | C10: Funcionalidade
B11: vf() | C11: Chamada de "Valor Futuro", que é utilizada para calcular o valor final de um investimento ou empréstimo com base em uma taxa de juros fixa e pagamentos constantes ao longo do tempo.
